Metadata-Version: 1.1
Name: textcleaner
Version: 0.4.23
Summary: textcleaner: text-data pre-processing library
Home-page: https://github.com/YugantM
Author: Yugant Hadiyal
Author-email: hadiyalyugant@gmail.com
License: MIT
Download-URL: https://github.com/USER/PROJECT/tarball/master
Keywords: MEANINGFULL,NLP,DATASCIENCE,DATACLEANING,PREPROCESSING
Platform: UNKNOWN
Classifier: Development Status :: 3 - Alpha
Classifier: Intended Audience :: Developers
Classifier: Topic :: Software Development :: Build Tools
Classifier: License :: OSI Approved :: MIT License
Classifier: Programming Language :: Python :: 3
Classifier: Programming Language :: Python :: 3.4
Classifier: Programming Language :: Python :: 3.5
Classifier: Programming Language :: Python :: 3.6
